django_health-0.4.dist-info/DESCRIPTION.rst
django_health-0.4.dist-info/METADATA
django_health-0.4.dist-info/metadata.json
django_health-0.4.dist-info/RECORD
django_health-0.4.dist-info/top_level.txt
django_health-0.4.dist-info/WHEEL
health/__init__.py
health/admin.py
health/defaults.py
health/models.py
health/tests.py
health/urls.py
health/views.py
