Metadata-Version: 2.0
Name: django-health
Version: 0.4
Summary: An easy way to see the health of your app
Home-page: ...
Author: John David Back
Author-email: john@casamatic.com
License: BSD License
Platform: UNKNOWN
Classifier: Environment :: Web Environment
Classifier: Framework :: Django
Classifier: Intended Audience :: Developers
Classifier: License :: OSI Approved :: BSD License
Classifier: Operating System :: OS Independent
Classifier: Programming Language :: Python
Classifier: Programming Language :: Python :: 3.3
Classifier: Topic :: Internet :: WWW/HTTP
